pypika_gis/dialects/MSSQLSpatial.py
pypika_gis/dialects/PostGIS.py
pypika_gis/spatialtypes.py
pypika_gis/test_mssql_spatialtypes.py
pypika_gis/test_postgis_spatialtypes.py
pypika_gis-2.0.0.dist-info/LICENSE
pypika_gis-2.0.0.dist-info/WHEEL
pypika_gis-2.0.0.dist-info/METADATA
pypika_gis-2.0.0.dist-info/RECORD
