Metadata-Version: 2.1
Name: pypika-gis
Version: 2.0.0
Summary: SpatialTypes functions for extend PyPika with GIS
Home-page: https://github.com/eduardogspereira/pypika-gis
Keywords: pypika,gis,postgis,sql,builder
Author: Eduardo G. S. Pereira
Author-email: edu_vcd@hotmail.com
Requires-Python: >=3.6.1
Classifier: Programming Language :: Python :: 3
Classifier: Programming Language :: Python :: 3.10
Classifier: Programming Language :: Python :: 3.7
Classifier: Programming Language :: Python :: 3.8
Classifier: Programming Language :: Python :: 3.9
Requires-Dist: PyPika (<1.0.0)
Project-URL: Repository, https://github.com/eduardogspereira/pypika-gis
